dbsnapshot/__init__.py
dbsnapshot/admin.py
dbsnapshot/client.py
dbsnapshot/defaults.py
dbsnapshot/models.py
dbsnapshot/tasks.py
dbsnapshot/locale/ru/LC_MESSAGES/django.po
dbsnapshot/management/__init__.py
dbsnapshot/management/commands/__init__.py
dbsnapshot/management/commands/run_dbsnapshot_server.py
dbsnapshot/management/commands/test_client.py
dbsnapshot/migrations/0001_initial.py
dbsnapshot/migrations/0002_auto__add_field_server_created__add_field_server_updated__add_field_se.py
dbsnapshot/migrations/0003_auto__add_log.py
dbsnapshot/migrations/__init__.py
django_db_snapshot-1.0.b.dist-info/DESCRIPTION.rst
django_db_snapshot-1.0.b.dist-info/METADATA
django_db_snapshot-1.0.b.dist-info/metadata.json
django_db_snapshot-1.0.b.dist-info/RECORD
django_db_snapshot-1.0.b.dist-info/top_level.txt
django_db_snapshot-1.0.b.dist-info/WHEEL
docs/__init__.py
docs/conf.py
